README.md
README.rst
setup.py
transgit/__init__.py
transgit/actions.py
transgit/cli.py
transgit/colors.py
transgit/constants.py
transgit/exceptions.py
transgit/utils.py
transgit.egg-info/PKG-INFO
transgit.egg-info/SOURCES.txt
transgit.egg-info/dependency_links.txt
transgit.egg-info/entry_points.txt
transgit.egg-info/not-zip-safe
transgit.egg-info/requires.txt
transgit.egg-info/top_level.txt