Metadata-Version: 2.1
Name: transgit
Version: 1.0.1
Summary: Open source tool to export Gitlab repositories to Github.
Home-page: https://github.com/pedrohavay/transgit
Author: Pedro Havay
Author-email: pedrohavay@outlook.com
Maintainer: Pedro Havay
License: UNKNOWN
Keywords: Git,Github,Gitlab
Platform: any
Requires-Python: >=3.5
